docker_dev_python.py
docker_dev_python-1.0a3.dist-info/pbr.json
docker_dev_python-1.0a3.dist-info/WHEEL
docker_dev_python-1.0a3.dist-info/metadata.json
docker_dev_python-1.0a3.dist-info/DESCRIPTION.rst
docker_dev_python-1.0a3.dist-info/METADATA
docker_dev_python-1.0a3.dist-info/top_level.txt
docker_dev_python-1.0a3.dist-info/entry_points.txt
docker_dev_python-1.0a3.dist-info/RECORD
