Metadata-Version: 2.0
Name: docker-dev-python
Version: 1.0a3
Summary: Python plugin for development tools for Docker
Home-page: https://github.com/2degrees/docker-dev-python
Author: 2degrees
Author-email: 2degrees-floss@googlegroups.com
License: UNKNOWN
Platform: UNKNOWN
Requires-Dist: docker-dev (>=1.0a2)
